[
    {
        "key": "dbln",
        "value": "%7B%2261580198067232%22%3A%22llhXJq1x%22%7D",
        "domain": "facebook.com",
        "path": "/login/device-based/",
        "hostOnly": false,
        "creation": "2025-09-02T05:33:43.807Z",
        "lastAccessed": "2025-09-02T05:33:43.807Z"
    },
    {
        "key": "sb",
        "value": "nIm0aG5fZNBSKf6E9Dhc12wQ",
        "domain": "facebook.com",
        "path": "/",
        "hostOnly": false,
        "creation": "2025-09-02T05:33:43.807Z",
        "lastAccessed": "2025-09-02T05:33:43.807Z"
    },
    {
        "key": "ps_l",
        "value": "1",
        "domain": "facebook.com",
        "path": "/",
        "hostOnly": false,
        "creation": "2025-09-02T05:33:43.807Z",
        "lastAccessed": "2025-09-02T05:33:43.807Z"
    },
    {
        "key": "ps_n",
        "value": "1",
        "domain": "facebook.com",
        "path": "/",
        "hostOnly": false,
        "creation": "2025-09-02T05:33:43.807Z",
        "lastAccessed": "2025-09-02T05:33:43.807Z"
    },
    {
        "key": "vpd",
        "value": "v1%3B692x360x3",
        "domain": "facebook.com",
        "path": "/",
        "hostOnly": false,
        "creation": "2025-09-02T05:33:43.807Z",
        "lastAccessed": "2025-09-02T05:33:43.807Z"
    },
    {
        "key": "dpr",
        "value": "3.2983407974243164",
        "domain": "facebook.com",
        "path": "/",
        "hostOnly": false,
        "creation": "2025-09-02T05:33:43.807Z",
        "lastAccessed": "2025-09-02T05:33:43.807Z"
    },
    {
        "key": "datr",
        "value": "K2C2aOszlqieDbWt0SRq4QL8",
        "domain": "facebook.com",
        "path": "/",
        "hostOnly": false,
        "creation": "2025-09-02T05:33:43.807Z",
        "lastAccessed": "2025-09-02T05:33:43.807Z"
    },
    {
        "key": "m_pixel_ratio",
        "value": "3",
        "domain": "facebook.com",
        "path": "/",
        "hostOnly": false,
        "creation": "2025-09-02T05:33:43.807Z",
        "lastAccessed": "2025-09-02T05:33:43.807Z"
    },
    {
        "key": "wd",
        "value": "360x800",
        "domain": "facebook.com",
        "path": "/",
        "hostOnly": false,
        "creation": "2025-09-02T05:33:43.807Z",
        "lastAccessed": "2025-09-02T05:33:43.807Z"
    },
    {
        "key": "locale",
        "value": "hi_IN",
        "domain": "facebook.com",
        "path": "/",
        "hostOnly": false,
        "creation": "2025-09-02T05:33:43.807Z",
        "lastAccessed": "2025-09-02T05:33:43.807Z"
    },
    {
        "key": "pas",
        "value": "61575781456684%3AG1cNXvcsXO%2C100078290935584%3A5H0bMu8fdd%2C61580198067232%3Avs8MveqFUI",
        "domain": "facebook.com",
        "path": "/",
        "hostOnly": false,
        "creation": "2025-09-02T05:33:43.807Z",
        "lastAccessed": "2025-09-02T05:33:43.807Z"
    },
    {
        "key": "c_user",
        "value": "61580198067232",
        "domain": "facebook.com",
        "path": "/",
        "hostOnly": false,
        "creation": "2025-09-02T05:33:43.807Z",
        "lastAccessed": "2025-09-02T05:33:43.807Z"
    },
    {
        "key": "xs",
        "value": "38%3AS0_KwaBB64tMTQ%3A2%3A1756791215%3A-1%3A-1",
        "domain": "facebook.com",
        "path": "/",
        "hostOnly": false,
        "creation": "2025-09-02T05:33:43.807Z",
        "lastAccessed": "2025-09-02T05:33:43.807Z"
    },
    {
        "key": "fr",
        "value": "0CKRDomqcRE5LaO2T.AWfkmCayTMGPzKWB8R0QgmcjTE1ML65Ku7sRbEP4zFuvWpsGYoA.BotImc..AAA.0.0.BotoGw.AWcNEUQDY_3SSJcXxOKGJMY9Zms",
        "domain": "facebook.com",
        "path": "/",
        "hostOnly": false,
        "creation": "2025-09-02T05:33:43.807Z",
        "lastAccessed": "2025-09-02T05:33:43.807Z"
    },
    {
        "key": "fbl_st",
        "value": "101318615%3BT%3A29279853",
        "domain": "facebook.com",
        "path": "/",
        "hostOnly": false,
        "creation": "2025-09-02T05:33:43.807Z",
        "lastAccessed": "2025-09-02T05:33:43.807Z"
    },
    {
        "key": "wl_cbv",
        "value": "v2%3Bclient_version%3A2910%3Btimestamp%3A1756791216",
        "domain": "facebook.com",
        "path": "/",
        "hostOnly": false,
        "creation": "2025-09-02T05:33:43.807Z",
        "lastAccessed": "2025-09-02T05:33:43.807Z"
    }
]
